{"stats":{"minecraft:picked_up":{"minecraft:warped_planks":2,"minecraft:dripstone_block":14,"minecraft:red_bed":3},"minecraft:used":{"minecraft:dripstone_block":13,"minecraft:warped_planks":1,"minecraft:red_bed":15},"minecraft:custom":{"minecraft:jump":50,"minecraft:time_since_rest":174508,"minecraft:crouch_one_cm":1070,"minecraft:leave_game":5,"minecraft:play_time":174508,"minecraft:sprint_one_cm":2105,"minecraft:time_since_death":174508,"minecraft:walk_one_cm":3602,"minecraft:sneak_time":328,"minecraft:total_world_time":174897,"minecraft:drop":19,"minecraft:fly_one_cm":5182},"minecraft:dropped":{"minecraft:red_bed":3,"minecraft:warped_planks":2,"minecraft:dripstone_block":14}},"DataVersion":3120}